formica/__init__.py
formica/aws.py
formica/aws_base.py
formica/change_set.py
formica/cli.py
formica/diff.py
formica/exceptions.py
formica/helper.py
formica/loader.py
formica/s3.py
formica/stack_set.py
formica/stack_waiter.py
formica/yaml_tags.py
formica_cli-0.16.1.dist-info/LICENSE
formica_cli-0.16.1.dist-info/METADATA
formica_cli-0.16.1.dist-info/WHEEL
formica_cli-0.16.1.dist-info/entry_points.txt
formica_cli-0.16.1.dist-info/top_level.txt
formica_cli-0.16.1.dist-info/RECORD
