Metadata-Version: 2.1
Name: formica-cli
Version: 0.16.1
Summary: Simple AWS CloudFormation stack management tooling.
Home-page: https://github.com/flomotlik/formica
Author: Florian Motlik
Author-email: flo@flomotlik.me
License: MIT
Keywords: cloudformation,aws,cloud
Platform: UNKNOWN
Classifier: Intended Audience :: Developers
Classifier: Topic :: Utilities
Classifier: License :: Public Domain
Classifier: Natural Language :: English
Classifier: Operating System :: OS Independent
Classifier: Programming Language :: Python :: 3
Classifier: Programming Language :: Python :: 3.6
Classifier: Programming Language :: Python :: 3.7
Requires-Python: >=3.6
License-File: LICENSE
Requires-Dist: boto3 (<2.0.0,>=1.18.35)
Requires-Dist: texttable (>=1.2.0)
Requires-Dist: jinja2 (>=3.0)
Requires-Dist: pyyaml (>=4.2b1)
Requires-Dist: deepdiff (>=5.0.0)
Requires-Dist: arrow (>=1.0.0)
Requires-Dist: argcomplete (>=1.9.4)
